ngsl
tests
