Metadata-Version: 2.1
Name: ngsl
Version: 1.21
Summary: You can check if the word is in New General Service List
Home-page: https://github.com/koboriakira/ngsl
Author: Kobori Akira
Author-email: private.beats@gmail.com
License: UNKNOWN
Platform: UNKNOWN
